{"command": "GetReportURL", "description": "This command allows to get different lists in CSV format, e.g. a daily created list of domain names or subusers. It returns a unique URL for each requested report, so the reports can be downloaded by the user. For security reasons the URL will only be accepted within a short period of time.", "availability": "All users have access to this command.", "paramaters": [{"Parameter": "COMMAND", "Min": "1", "Definition": "GetReportURL", "Type": "COMMAND"}, {"Parameter": "FILE", "Min": "1", "Definition": "Report name:domains.csv - list of domain names, which belong to the user, executing the command, and its subusers. This list created on a daily basisusers.csv - subusers list of the user, executing the command. This list created on a daily basis", "Type": "TEXT"}, {"Parameter": "USERDEPTH", "Min": "0", "Definition": "Depth of the list, may be SELF, SUBUSER or ALL", "Type": "SELF, SUBUSER or ALL"}]}