{"command": "QueryEventList", "description": "Query a list of events.", "availability": "All users have access to this command. This command does not make sense if your useraccount does not have any subusers.", "paramaters": [{"Parameter": "COMMAND", "Min": "1", "Definition": "QueryEventList", "Type": "COMMAND"}, {"Parameter": "WIDE", "Min": "0", "Definition": "Returns some more properties if set to 1", "Type": "1 or 0"}, {"Parameter": "FIRST", "Min": "0", "Definition": "Index of the first entry to be returned", "Type": "INT"}, {"Parameter": "LIMIT", "Min": "0", "Definition": "Max. number of entries to be returned, if set to ONLYLAST only the latest event will be returned", "Type": "INT or ONLYLAST"}, {"Parameter": "CLASS", "Min": "0", "Definition": "Event class, e.g. DOMAIN_TRANSFER", "Type": "PATTERN"}, {"Parameter": "SUBCLASS", "Min": "0", "Definition": "Event subclass, e.g. TRANSFER_SUCCESSFUL", "Type": "PATTERN"}, {"Parameter": "MINDATE", "Min": "0", "Definition": "First event date to be returned", "Type": "NULL or TEXT"}, {"Parameter": "MAXDATE", "Min": "0", "Definition": "Last event date to be returned", "Type": "NULL or TEXT"}, {"Parameter": "ORDERBY", "Min": "0", "Definition": "Order response by response parameters; switch order by adding DESC to response parameter, e.g.: EVENTDATE or EVENTDATEDESC", "Type": "EVENTDATE, EVENTDATEDESC or NULL"}]}