{"a": {"/": "", "i": {"/": ""}, "n": {"/": "", "g": {"/": ""}}, "o": {"/": ""}}, "b": {"a": {"/": "", "i": {"/": ""}, "n": {"/": "", "g": {"/": ""}}, "o": {"/": ""}}, "e": {"i": {"/": ""}, "n": {"/": "", "g": {"/": ""}}}, "i": {"/": "", "a": {"n": {"/": ""}, "o": {"/": ""}}, "e": {"/": ""}, "n": {"/": "", "g": {"/": ""}}}, "o": {"/": ""}, "u": {"/": ""}}, "c": {"a": {"/": "", "i": {"/": ""}, "n": {"/": "", "g": {"/": ""}}, "o": {"/": ""}}, "e": {"/": "", "n": {"/": "", "g": {"/": ""}}}, "h": {"a": {"/": "", "i": {"/": ""}, "n": {"/": "", "g": {"/": ""}}, "o": {"/": ""}}, "e": {"/": "", "n": {"/": "", "g": {"/": ""}}}, "i": {"/": "", "a": {"/": "", "n": {"g": {"/": ""}}, "o": {"/": ""}}, "e": {"h": {"/": ""}, "n": {"/": ""}}, "h": {"/": ""}, "n": {"/": "", "g": {"/": ""}}, "u": {"/": "", "n": {"g": {"/": ""}}}}, "o": {"/": "", "n": {"g": {"/": ""}}, "u": {"/": ""}}, "u": {"/": "", "a": {"/": "", "i": {"/": ""}, "n": {"/": "", "g": {"/": ""}}}, "e": {"h": {"/": ""}}, "i": {"/": ""}, "n": {"/": "", "g": {"/": ""}}, "o": {"/": ""}}, "ü": {"/": "", "a": {"n": {"/": ""}}, "e": {"h": {"/": ""}}, "n": {"/": ""}}}, "i": {"/": ""}, "o": {"n": {"g": {"/": ""}}, "u": {"/": ""}}, "u": {"/": "", "a": {"n": {"/": ""}}, "i": {"/": ""}, "n": {"/": ""}, "o": {"/": ""}}}, "d": {"a": {"/": "", "i": {"/": ""}, "n": {"/": "", "g": {"/": ""}}, "o": {"/": ""}}, "e": {"/": "", "i": {"/": ""}, "n": {"g": {"/": ""}}}, "i": {"/": "", "a": {"n": {"/": ""}, "o": {"/": ""}}, "e": {"/": ""}, "n": {"g": {"/": ""}}, "u": {"/": ""}}, "o": {"n": {"g": {"/": ""}}, "u": {"/": ""}}, "u": {"/": "", "a": {"n": {"/": ""}}, "i": {"/": ""}, "n": {"/": ""}, "o": {"/": ""}}}, "e": {"/": "", "i": {"/": ""}, "n": {"/": "", "g": {"/": ""}}, "r": {"/": "", "h": {"/": ""}}}, "f": {"a": {"/": "", "n": {"/": "", "g": {"/": ""}}}, "e": {"i": {"/": ""}, "n": {"/": "", "g": {"/": ""}}}, "o": {"/": "", "u": {"/": ""}}, "u": {"/": ""}}, "g": {"a": {"/": "", "i": {"/": ""}, "n": {"/": "", "g": {"/": ""}}, "o": {"/": ""}}, "e": {"/": "", "i": {"/": ""}, "n": {"/": "", "g": {"/": ""}}}, "o": {"n": {"g": {"/": ""}}, "u": {"/": ""}}, "u": {"/": "", "a": {"/": "", "i": {"/": ""}, "n": {"/": "", "g": {"/": ""}}}, "i": {"/": ""}, "n": {"/": ""}, "o": {"/": ""}}}, "h": {"a": {"/": "", "i": {"/": ""}, "n": {"/": "", "g": {"/": ""}}, "o": {"/": ""}, "u": {"/": ""}, "w": {"/": ""}}, "e": {"/": "", "e": {"/": ""}, "i": {"/": ""}, "n": {"/": "", "g": {"/": ""}}}, "o": {"/": "", "n": {"g": {"/": ""}}, "u": {"/": ""}}, "s": {"i": {"/": "", "a": {"/": "", "n": {"g": {"/": ""}}, "o": {"/": ""}}, "e": {"h": {"/": ""}, "n": {"/": ""}}, "n": {"/": "", "g": {"/": ""}}, "u": {"/": "", "n": {"g": {"/": ""}}}}, "u": {"/": "", "a": {"n": {"/": ""}}, "e": {"h": {"/": ""}}, "n": {"/": ""}}, "ü": {"/": "", "a": {"n": {"/": ""}}, "e": {"h": {"/": ""}}, "n": {"/": ""}}}, "u": {"/": "", "a": {"/": "", "i": {"/": ""}, "n": {"/": "", "g": {"/": ""}}}, "i": {"/": ""}, "n": {"/": "", "g": {"/": ""}}, "o": {"/": ""}}, "y": {"u": {"n": {"/": ""}}}}, "j": {"a": {"n": {"/": "", "g": {"/": ""}}, "o": {"/": ""}}, "e": {"/": "", "n": {"/": "", "g": {"/": ""}}}, "i": {"/": "", "a": {"/": "", "n": {"/": "", "g": {"/": ""}}, "o": {"/": ""}}, "e": {"/": ""}, "h": {"/": ""}, "n": {"/": "", "g": {"/": ""}}, "o": {"n": {"g": {"/": ""}}}, "u": {"/": ""}}, "o": {"/": "", "u": {"/": ""}}, "u": {"/": "", "a": {"n": {"/": ""}}, "e": {"/": ""}, "i": {"/": ""}, "n": {"/": "", "g": {"/": ""}}}}, "k": {"a": {"/": "", "i": {"/": ""}, "n": {"/": "", "g": {"/": ""}}, "o": {"/": ""}, "w": {"/": ""}}, "e": {"/": "", "n": {"/": "", "g": {"/": ""}}}, "i": {"m": {"/": ""}}, "o": {"/": "", "n": {"g": {"/": ""}}, "o": {"/": ""}, "u": {"/": ""}, "w": {"/": ""}}, "u": {"/": "", "a": {"/": "", "i": {"/": ""}, "n": {"/": "", "g": {"/": ""}}}, "e": {"i": {"/": ""}}, "i": {"/": ""}, "n": {"/": "", "g": {"/": ""}}, "o": {"/": ""}}, "w": {"o": {"/": "", "n": {"g": {"/": ""}}}}}, "l": {"a": {"/": "", "i": {"/": ""}, "n": {"/": "", "g": {"/": ""}}, "o": {"/": ""}}, "e": {"/": "", "e": {"/": ""}, "i": {"/": ""}, "n": {"g": {"/": ""}}}, "i": {"/": "", "a": {"/": "", "n": {"/": "", "g": {"/": ""}}, "o": {"/": ""}}, "e": {"/": "", "h": {"/": ""}, "n": {"/": ""}}, "n": {"/": "", "g": {"/": ""}}, "u": {"/": ""}}, "o": {"/": "", "n": {"g": {"/": ""}}, "u": {"/": ""}}, "u": {"/": "", "a": {"n": {"/": ""}}, "e": {"/": "", "h": {"/": ""}}, "n": {"/": "", "g": {"/": ""}}, "o": {"/": ""}}, "v": {"/": "", "e": {"/": ""}}, "ü": {"/": "", "a": {"n": {"/": ""}}, "e": {"/": "", "h": {"/": ""}}}}, "m": {"a": {"/": "", "i": {"/": ""}, "n": {"/": "", "g": {"/": ""}}, "o": {"/": ""}, "u": {"/": ""}, "w": {"/": ""}}, "e": {"/": "", "i": {"/": ""}, "n": {"/": "", "g": {"/": ""}}}, "i": {"/": "", "a": {"n": {"/": ""}, "o": {"/": ""}}, "e": {"/": "", "h": {"/": ""}, "n": {"/": ""}}, "n": {"/": "", "g": {"/": ""}}, "u": {"/": ""}}, "o": {"/": "", "u": {"/": ""}}, "u": {"/": "", "n": {"/": "", "g": {"/": ""}}}}, "n": {"a": {"/": "", "i": {"/": ""}, "n": {"/": "", "g": {"/": ""}}, "o": {"/": ""}}, "e": {"/": "", "i": {"/": ""}, "n": {"/": "", "g": {"/": ""}}}, "g": {"/": ""}, "i": {"/": "", "a": {"n": {"/": "", "g": {"/": ""}}, "o": {"/": ""}}, "e": {"/": "", "h": {"/": ""}, "n": {"/": ""}}, "n": {"/": "", "g": {"/": ""}}, "u": {"/": ""}}, "o": {"/": "", "n": {"g": {"/": ""}}, "u": {"/": ""}}, "u": {"/": "", "a": {"n": {"/": ""}}, "e": {"/": "", "h": {"/": ""}}, "n": {"g": {"/": ""}}, "o": {"/": ""}}, "v": {"/": "", "e": {"/": ""}}, "ü": {"/": "", "e": {"/": "", "h": {"/": ""}}}}, "o": {"/": "", "u": {"/": ""}}, "p": {"a": {"/": "", "i": {"/": ""}, "n": {"/": "", "g": {"/": ""}}, "o": {"/": ""}}, "e": {"i": {"/": ""}, "n": {"/": "", "g": {"/": ""}}}, "i": {"/": "", "a": {"n": {"/": ""}, "o": {"/": ""}}, "e": {"/": "", "h": {"/": ""}, "n": {"/": ""}}, "n": {"/": "", "g": {"/": ""}}}, "o": {"/": "", "u": {"/": ""}}, "u": {"/": ""}}, "q": {"i": {"/": "", "a": {"/": "", "n": {"/": "", "g": {"/": ""}}, "o": {"/": ""}}, "e": {"/": ""}, "n": {"/": "", "g": {"/": ""}}, "o": {"n": {"g": {"/": ""}}}, "u": {"/": ""}}, "u": {"/": "", "a": {"n": {"/": ""}}, "e": {"/": ""}, "n": {"/": ""}}, "v": {"e": {"/": ""}}, "ü": {"e": {"/": ""}}}, "r": {"a": {"n": {"/": "", "g": {"/": ""}}, "o": {"/": ""}}, "e": {"/": "", "n": {"/": "", "g": {"/": ""}}}, "i": {"/": ""}, "o": {"n": {"g": {"/": ""}}, "u": {"/": ""}}, "u": {"/": "", "a": {"n": {"/": ""}}, "i": {"/": ""}, "n": {"/": ""}, "o": {"/": ""}}}, "s": {"a": {"/": "", "i": {"/": ""}, "n": {"/": "", "g": {"/": ""}}, "o": {"/": ""}}, "e": {"/": "", "n": {"/": "", "g": {"/": ""}}}, "h": {"a": {"/": "", "i": {"/": ""}, "n": {"/": "", "g": {"/": ""}}, "o": {"/": ""}}, "e": {"/": "", "i": {"/": ""}, "n": {"/": "", "g": {"/": ""}}}, "i": {"/": "", "h": {"/": ""}}, "o": {"u": {"/": ""}}, "u": {"/": "", "a": {"/": "", "i": {"/": ""}, "n": {"/": "", "g": {"/": ""}}}, "i": {"/": ""}, "n": {"/": ""}, "o": {"/": ""}}}, "i": {"/": ""}, "o": {"/": "", "n": {"g": {"/": ""}}, "u": {"/": ""}}, "s": {"u": {"/": ""}}, "u": {"/": "", "a": {"n": {"/": ""}}, "i": {"/": ""}, "n": {"/": "", "g": {"/": ""}}, "o": {"/": ""}}}, "t": {"a": {"/": "", "i": {"/": ""}, "n": {"/": "", "g": {"/": ""}}, "o": {"/": ""}}, "e": {"/": "", "n": {"g": {"/": ""}}}, "i": {"/": "", "a": {"n": {"/": ""}, "o": {"/": ""}}, "e": {"/": "", "h": {"/": ""}, "n": {"/": ""}}, "n": {"g": {"/": ""}}, "u": {"/": ""}}, "o": {"/": "", "n": {"g": {"/": ""}}, "u": {"/": ""}}, "s": {"a": {"/": "", "i": {"/": ""}, "n": {"/": "", "g": {"/": ""}}, "o": {"/": ""}}, "e": {"/": "", "i": {"/": ""}, "n": {"/": "", "g": {"/": ""}}}, "o": {"/": "", "u": {"/": ""}}, "u": {"/": "", "a": {"n": {"/": ""}}, "i": {"/": ""}, "n": {"/": "", "g": {"/": ""}}}}, "u": {"/": "", "a": {"n": {"/": ""}}, "i": {"/": ""}, "n": {"/": "", "g": {"/": ""}}, "o": {"/": ""}}, "z": {"u": {"/": ""}}}, "w": {"a": {"/": "", "i": {"/": ""}, "n": {"/": "", "g": {"/": ""}}}, "e": {"i": {"/": ""}, "n": {"/": "", "g": {"/": ""}}}, "o": {"/": ""}, "u": {"/": ""}}, "x": {"i": {"/": "", "a": {"/": "", "n": {"/": "", "g": {"/": ""}}, "o": {"/": ""}}, "e": {"/": ""}, "n": {"/": "", "g": {"/": ""}}, "o": {"n": {"g": {"/": ""}}}, "u": {"/": "", "a": {"n": {"/": ""}}, "e": {"/": ""}}}, "u": {"/": "", "a": {"n": {"/": ""}}, "e": {"/": ""}, "n": {"/": ""}}}, "y": {"a": {"/": "", "e": {"/": ""}, "i": {"/": ""}, "n": {"/": "", "g": {"/": ""}}, "o": {"/": ""}, "t": {"/": ""}}, "e": {"/": "", "a": {"/": "", "n": {"/": "", "g": {"/": ""}}}, "h": {"/": ""}, "n": {"/": "", "g": {"/": ""}}, "o": {"n": {"/": "", "g": {"/": ""}}, "u": {"/": ""}}, "u": {"/": "", "l": {"/": ""}, "n": {"/": "", "g": {"/": ""}}}}, "i": {"/": "", "a": {"/": "", "n": {"/": ""}}, "n": {"/": "", "g": {"/": ""}}, "o": {"n": {"g": {"/": ""}}}, "u": {"/": "", "a": {"n": {"/": ""}}, "n": {"/": "", "g": {"/": ""}}}}, "o": {"/": "", "n": {"g": {"/": ""}}, "u": {"/": "", "n": {"g": {"/": ""}}}}, "u": {"/": "", "a": {"n": {"/": ""}}, "e": {"/": "", "h": {"/": ""}}, "n": {"/": "", "g": {"/": ""}}}, "v": {"e": {"/": ""}}, "ü": {"/": "", "a": {"n": {"/": ""}}, "e": {"/": "", "h": {"/": ""}}, "n": {"/": ""}}}, "z": {"a": {"/": "", "i": {"/": ""}, "n": {"/": "", "g": {"/": ""}}, "o": {"/": ""}}, "e": {"/": "", "i": {"/": ""}, "n": {"/": "", "g": {"/": ""}}}, "h": {"a": {"/": "", "i": {"/": ""}, "n": {"/": "", "g": {"/": ""}}, "o": {"/": ""}}, "e": {"/": "", "n": {"/": "", "g": {"/": ""}}}, "i": {"/": ""}, "o": {"n": {"g": {"/": ""}}, "u": {"/": ""}}, "u": {"/": "", "a": {"/": "", "i": {"/": ""}, "n": {"/": "", "g": {"/": ""}}}, "i": {"/": ""}, "n": {"/": ""}, "o": {"/": ""}}}, "i": {"/": ""}, "o": {"n": {"g": {"/": ""}}, "u": {"/": ""}}, "u": {"/": "", "a": {"n": {"/": ""}}, "i": {"/": ""}, "n": {"/": ""}, "o": {"/": ""}}}}